[{"id":"k051","character":"女","onyomi":["じょ"],"kunyomi":[],"meaning":"女～（things done by women）","examples":[{"word":"女～","reading":"じょ～","meaning":"女～（things done by women）"},{"word":"～女","reading":"～じょ","meaning":"～女（count for sisters）"},{"word":"女の人","reading":"おんなのひと","meaning":"女の人（woman）"}],"jlptLevel":"N2"},{"id":"k052","character":"省","onyomi":["しょ"],"kunyomi":[],"meaning":"省～（economizing ~）","examples":[{"word":"省～","reading":"しょう～","meaning":"省～（economizing ~）"},{"word":"～省","reading":"～しょう","meaning":"～省（kind of ministry）"}],"jlptLevel":"N2"},{"id":"k053","character":"商","onyomi":["～し"],"kunyomi":[],"meaning":"～商（merchant","examples":[{"word":"～商","reading":"～しょう","meaning":"～商（merchant, business）"},{"word":"商業","reading":"しょうぎょう","meaning":"商業（commerce, trade, business）"},{"word":"商社","reading":"しょうしゃ","meaning":"商社（trading company）"}],"jlptLevel":"N2"},{"id":"k054","character":"勝","onyomi":["～し"],"kunyomi":[],"meaning":"～勝（count for victory）","examples":[{"word":"～勝","reading":"～しょう","meaning":"～勝（count for victory）"},{"word":"勝敗","reading":"しょうはい","meaning":"勝敗（victory or defeat, issue (of battle)）"},{"word":"勝負","reading":"しょうぶ","meaning":"勝負（victory or defeat, game）"}],"jlptLevel":"N2"},{"id":"k055","character":"条","onyomi":["～じ"],"kunyomi":[],"meaning":"～条（counter for article）","examples":[{"word":"～条","reading":"～じょう","meaning":"～条（counter for article）"}],"jlptLevel":"N2"},{"id":"k056","character":"場","onyomi":["～じ"],"kunyomi":[],"meaning":"～場（kind of field","examples":[{"word":"～場","reading":"～じょう","meaning":"～場（kind of field, ground）"},{"word":"職場","reading":"しょくば","meaning":"職場（workplace）"},{"word":"酒場","reading":"さかば","meaning":"酒場（bar, bar-room）"}],"jlptLevel":"N2"},{"id":"k057","character":"畳","onyomi":["～じ"],"kunyomi":[],"meaning":"～畳（count for tatami","examples":[{"word":"～畳","reading":"～じょう","meaning":"～畳（count for tatami, mat）"}],"jlptLevel":"N2"},{"id":"k058","character":"消","onyomi":["しょ"],"kunyomi":[],"meaning":"消化（digestion）","examples":[{"word":"消化","reading":"しょうか","meaning":"消化（digestion）"},{"word":"消極的","reading":"しょうきょくてき","meaning":"消極的（passive）"},{"word":"消毒","reading":"しょうどく","meaning":"消毒（disinfection）"}],"jlptLevel":"N2"},{"id":"k059","character":"化","onyomi":["しょ"],"kunyomi":[],"meaning":"消化（digestion）","examples":[{"word":"消化","reading":"しょうか","meaning":"消化（digestion）"},{"word":"～化","reading":"～か","meaning":"～化（action of making something）"},{"word":"強化","reading":"きょうか","meaning":"強化（strengthen, intensify, reinforce）"}],"jlptLevel":"N2"},{"id":"k060","character":"学","onyomi":["しょうが"],"kunyomi":[],"meaning":"小学生（elementary school pupil）","examples":[{"word":"小学生","reading":"しょうがくせい","meaning":"小学生（elementary school pupil）"},{"word":"人文科学","reading":"じんぶんかがく","meaning":"人文科学（social sciences, humanities）"},{"word":"大学院","reading":"だいがくいん","meaning":"大学院（graduate school）"}],"jlptLevel":"N2"},{"id":"k061","character":"生","onyomi":["しょうが"],"kunyomi":[],"meaning":"小学生（elementary school pupil）","examples":[{"word":"小学生","reading":"しょうがくせい","meaning":"小学生（elementary school pupil）"},{"word":"生ずる","reading":"しょうずる","meaning":"生ずる（to cause, to arise, to be generated）"},{"word":"生存","reading":"せいぞん","meaning":"生存（existence, being, survival）"}],"jlptLevel":"N2"},{"id":"k062","character":"将","onyomi":["しょ"],"kunyomi":[],"meaning":"将棋（Japanese chess）","examples":[{"word":"将棋","reading":"しょうぎ","meaning":"将棋（Japanese chess）"}],"jlptLevel":"N2"},{"id":"k063","character":"棋","onyomi":["しょ"],"kunyomi":[],"meaning":"将棋（Japanese chess）","examples":[{"word":"将棋","reading":"しょうぎ","meaning":"将棋（Japanese chess）"}],"jlptLevel":"N2"},{"id":"k064","character":"蒸","onyomi":["じょ"],"kunyomi":[],"meaning":"蒸気（steam","examples":[{"word":"蒸気","reading":"じょうき","meaning":"蒸気（steam, vapor）"},{"word":"蒸発","reading":"じょうはつ","meaning":"蒸発（evaporation; unexplained disappearance）"},{"word":"水蒸気","reading":"すいじょうき","meaning":"水蒸気（water vapor, steam）"}],"jlptLevel":"N2"},{"id":"k065","character":"気","onyomi":["じょ"],"kunyomi":[],"meaning":"蒸気（steam","examples":[{"word":"蒸気","reading":"じょうき","meaning":"蒸気（steam, vapor）"},{"word":"水蒸気","reading":"すいじょうき","meaning":"水蒸気（water vapor, steam）"},{"word":"お気の毒に","reading":"おきのどくに","meaning":"お気の毒に（I'm sorry to hear that…）"}],"jlptLevel":"N2"},{"id":"k066","character":"定","onyomi":["じょ"],"kunyomi":[],"meaning":"定規（(measuring) ruler）","examples":[{"word":"定規","reading":"じょうぎ","meaning":"定規（(measuring) ruler）"},{"word":"推定","reading":"すいてい","meaning":"推定（presumption, assumption, estimation）"},{"word":"測定","reading":"そくてい","meaning":"測定（measurement）"}],"jlptLevel":"N2"},{"id":"k067","character":"規","onyomi":["じょ"],"kunyomi":[],"meaning":"定規（(measuring) ruler）","examples":[{"word":"定規","reading":"じょうぎ","meaning":"定規（(measuring) ruler）"},{"word":"規準","reading":"きじゅん","meaning":"規準（standard, basis, criteria）"},{"word":"規律","reading":"きりつ","meaning":"規律（order, rules, law）"}],"jlptLevel":"N2"},{"id":"k068","character":"上","onyomi":["じょうき"],"kunyomi":[],"meaning":"上級（advanced level","examples":[{"word":"上級","reading":"じょうきゅう","meaning":"上級（advanced level, high grade, senior）"},{"word":"上下","reading":"じょうげ","meaning":"上下（high and low, up and down）"},{"word":"上旬","reading":"じょうじゅん","meaning":"上旬（first 10 days of month）"}],"jlptLevel":"N2"},{"id":"k069","character":"級","onyomi":["じょうき"],"kunyomi":[],"meaning":"上級（advanced level","examples":[{"word":"上級","reading":"じょうきゅう","meaning":"上級（advanced level, high grade, senior）"},{"word":"初級","reading":"しょきゅう","meaning":"初級（elementary level）"},{"word":"学級","reading":"がっきゅう","meaning":"学級（class）"}],"jlptLevel":"N2"},{"id":"k070","character":"業","onyomi":["しょうぎ"],"kunyomi":[],"meaning":"商業（commerce","examples":[{"word":"商業","reading":"しょうぎょう","meaning":"商業（commerce, trade, business）"},{"word":"休業","reading":"きゅうぎょう","meaning":"休業（closure, shutdown, holiday）"},{"word":"～業","reading":"～ぎょう","meaning":"～業（type of business）"}],"jlptLevel":"N2"},{"id":"k071","character":"極","onyomi":["しょうき"],"kunyomi":[],"meaning":"消極的（passive）","examples":[{"word":"消極的","reading":"しょうきょくてき","meaning":"消極的（passive）"},{"word":"南極","reading":"なんきょく","meaning":"南極（south pole, Antarctic）"},{"word":"北極","reading":"ほっきょく","meaning":"北極（North Pole）"}],"jlptLevel":"N2"},{"id":"k072","character":"的","onyomi":["しょうき"],"kunyomi":[],"meaning":"消極的（passive）","examples":[{"word":"消極的","reading":"しょうきょくてき","meaning":"消極的（passive）"},{"word":"比較的","reading":"ひかくてき","meaning":"比較的（comparatively; relatively）"},{"word":"的確","reading":"てきかく","meaning":"的確（precise, accurate）"}],"jlptLevel":"N2"},{"id":"k073","character":"賞","onyomi":["しょうき"],"kunyomi":[],"meaning":"賞金（prize","examples":[{"word":"賞金","reading":"しょうきん","meaning":"賞金（prize, monetary award）"},{"word":"鑑賞","reading":"かんしょう","meaning":"鑑賞（appreciation）"}],"jlptLevel":"N2"},{"id":"k074","character":"金","onyomi":["しょうき"],"kunyomi":[],"meaning":"賞金（prize","examples":[{"word":"賞金","reading":"しょうきん","meaning":"賞金（prize, monetary award）"},{"word":"金魚","reading":"きんぎょ","meaning":"金魚（goldfish）"},{"word":"集金","reading":"しゅうきん","meaning":"集金（money collection）"}],"jlptLevel":"N2"},{"id":"k075","character":"下","onyomi":["じょ"],"kunyomi":[],"meaning":"上下（high and low","examples":[{"word":"上下","reading":"じょうげ","meaning":"上下（high and low, up and down）"},{"word":"～下","reading":"～か","meaning":"～下（under ~）"},{"word":"下降","reading":"かこう","meaning":"下降（decline, descent, fall）"}],"jlptLevel":"N2"},{"id":"k076","character":"障","onyomi":["しょ"],"kunyomi":[],"meaning":"障子（paper sliding door）","examples":[{"word":"障子","reading":"しょうじ","meaning":"障子（paper sliding door）"}],"jlptLevel":"N2"},{"id":"k077","character":"子","onyomi":["しょ"],"kunyomi":[],"meaning":"障子（paper sliding door）","examples":[{"word":"障子","reading":"しょうじ","meaning":"障子（paper sliding door）"},{"word":"末っ子","reading":"すえっこ","meaning":"末っ子（youngest child）"},{"word":"扇子","reading":"せんす","meaning":"扇子（folding fan）"}],"jlptLevel":"N2"},{"id":"k078","character":"社","onyomi":["しょうし"],"kunyomi":[],"meaning":"商社（trading company）","examples":[{"word":"商社","reading":"しょうしゃ","meaning":"商社（trading company）"},{"word":"～社","reading":"～しゃ","meaning":"～社（counter for company）"},{"word":"社会科学","reading":"しゃかいかがく","meaning":"社会科学（social science）"}],"jlptLevel":"N2"},{"id":"k079","character":"乗","onyomi":["じょうし"],"kunyomi":[],"meaning":"乗車（taking a train","examples":[{"word":"乗車","reading":"じょうしゃ","meaning":"乗車（taking a train, entraining）"},{"word":"乗換","reading":"のりかえ","meaning":"乗換（a transfer (e.g., trains, buses)）"},{"word":"乗り越し","reading":"のりこし","meaning":"乗り越し（riding past (one's station)）"}],"jlptLevel":"N2"},{"id":"k080","character":"車","onyomi":["じょうし"],"kunyomi":[],"meaning":"乗車（taking a train","examples":[{"word":"乗車","reading":"じょうしゃ","meaning":"乗車（taking a train, entraining）"},{"word":"機関車","reading":"きかんしゃ","meaning":"機関車（locomotive, engine）"},{"word":"下車","reading":"げしゃ","meaning":"下車（alighting, getting off）"}],"jlptLevel":"N2"},{"id":"k081","character":"旬","onyomi":["じょうじ"],"kunyomi":[],"meaning":"上旬（first 10 days of month）","examples":[{"word":"上旬","reading":"じょうじゅん","meaning":"上旬（first 10 days of month）"},{"word":"初旬","reading":"しょじゅん","meaning":"初旬（first 10 days of the month）"},{"word":"下旬","reading":"げじゅん","meaning":"下旬（month (last third of)）"}],"jlptLevel":"N2"},{"id":"k082","character":"数","onyomi":["しょうす"],"kunyomi":[],"meaning":"小数（fraction (part of)","examples":[{"word":"小数","reading":"しょうすう","meaning":"小数（fraction (part of), decimal）"},{"word":"整数","reading":"せいすう","meaning":"整数（integer）"},{"word":"回数","reading":"かいすう","meaning":"回数（number of times, frequency）"}],"jlptLevel":"N2"},{"id":"k083","character":"店","onyomi":["しょうて"],"kunyomi":[],"meaning":"商店（shop","examples":[{"word":"商店","reading":"しょうてん","meaning":"商店（shop, business firm）"},{"word":"書店","reading":"しょてん","meaning":"書店（bookshop）"},{"word":"売店","reading":"ばいてん","meaning":"売店（shop, stand）"}],"jlptLevel":"N2"},{"id":"k084","character":"焦","onyomi":["しょうて"],"kunyomi":[],"meaning":"焦点（focus","examples":[{"word":"焦点","reading":"しょうてん","meaning":"焦点（focus, point）"},{"word":"焦がす","reading":"こがす","meaning":"焦がす（to burn, to scorch）"},{"word":"焦げる","reading":"こげる","meaning":"焦げる（to burn, to be burned）"}],"jlptLevel":"N2"},{"id":"k085","character":"点","onyomi":["しょうて"],"kunyomi":[],"meaning":"焦点（focus","examples":[{"word":"焦点","reading":"しょうてん","meaning":"焦点（focus, point）"},{"word":"句読点","reading":"くとうてん","meaning":"句読点（punctuation marks）"},{"word":"採点","reading":"さいてん","meaning":"採点（marking, grading）"}],"jlptLevel":"N2"},{"id":"k086","character":"毒","onyomi":["しょうど"],"kunyomi":[],"meaning":"消毒（disinfection）","examples":[{"word":"消毒","reading":"しょうどく","meaning":"消毒（disinfection）"},{"word":"お気の毒に","reading":"おきのどくに","meaning":"お気の毒に（I'm sorry to hear that…）"}],"jlptLevel":"N2"},{"id":"k087","character":"敗","onyomi":["しょうは"],"kunyomi":[],"meaning":"勝敗（victory or defeat","examples":[{"word":"勝敗","reading":"しょうはい","meaning":"勝敗（victory or defeat, issue (of battle)）"}],"jlptLevel":"N2"},{"id":"k088","character":"発","onyomi":["じょうは"],"kunyomi":[],"meaning":"蒸発（evaporation","examples":[{"word":"蒸発","reading":"じょうはつ","meaning":"蒸発（evaporation; unexplained disappearance）"},{"word":"～発","reading":"～はつ","meaning":"～発（counter for bullets）"},{"word":"発揮","reading":"はっき","meaning":"発揮（exhibition, demonstration, display）"}],"jlptLevel":"N2"},{"id":"k089","character":"品","onyomi":["じょうひ"],"kunyomi":[],"meaning":"上品（refined","examples":[{"word":"上品","reading":"じょうひん","meaning":"上品（refined, elegant, well-mannered）"},{"word":"下品","reading":"げひん","meaning":"下品（vulgar, indecent, coarse）"},{"word":"日用品","reading":"にちようひん","meaning":"日用品（daily necessities）"}],"jlptLevel":"N2"},{"id":"k090","character":"負","onyomi":["しょ"],"kunyomi":[],"meaning":"勝負（victory or defeat","examples":[{"word":"勝負","reading":"しょうぶ","meaning":"勝負（victory or defeat, game）"},{"word":"背負う","reading":"せおう","meaning":"to be burdened with; to carry on (one's) back or shoulder(s)"}],"jlptLevel":"N2"},{"id":"k091","character":"便","onyomi":["しょうべ"],"kunyomi":[],"meaning":"小便（(col) urine","examples":[{"word":"小便","reading":"しょうべん","meaning":"小便（(col) urine, piss）"},{"word":"便箋","reading":"びんせん","meaning":"便箋（writing paper, stationery）"},{"word":"船便","reading":"ふなびん","meaning":"船便（surface mail (ship)）"}],"jlptLevel":"N2"},{"id":"k092","character":"防","onyomi":["しょうぼ"],"kunyomi":[],"meaning":"消防署（fire station）","examples":[{"word":"消防署","reading":"しょうぼうしょ","meaning":"消防署（fire station）"},{"word":"防～","reading":"ぼう～","meaning":"防～（~ prevention）"},{"word":"防止","reading":"ぼうし","meaning":"防止（prevention, check）"}],"jlptLevel":"N2"},{"id":"k093","character":"署","onyomi":["しょうぼ"],"kunyomi":[],"meaning":"消防署（fire station）","examples":[{"word":"消防署","reading":"しょうぼうしょ","meaning":"消防署（fire station）"}],"jlptLevel":"N2"},{"id":"k094","character":"正","onyomi":["しょ"],"kunyomi":[],"meaning":"正味（net (weight)）","examples":[{"word":"正味","reading":"しょうみ","meaning":"正味（net (weight)）"},{"word":"正面","reading":"しょうめん","meaning":"正面（front）"},{"word":"正方形","reading":"せいほうけい","meaning":"正方形（square）"}],"jlptLevel":"N2"},{"id":"k095","character":"味","onyomi":["しょ"],"kunyomi":[],"meaning":"正味（net (weight)）","examples":[{"word":"正味","reading":"しょうみ","meaning":"正味（net (weight)）"},{"word":"～気味","reading":"～ぎみ","meaning":"～気味（slightly ~）"},{"word":"味わう","reading":"あじわう","meaning":"味わう（to taste, to savor）"}],"jlptLevel":"N2"},{"id":"k096","character":"面","onyomi":["しょうめ"],"kunyomi":[],"meaning":"正面（front）","examples":[{"word":"正面","reading":"しょうめん","meaning":"正面（front）"},{"word":"水面","reading":"すいめん","meaning":"水面（water's surface）"},{"word":"洗面","reading":"せんめん","meaning":"洗面（wash up (one's face), have a wash）"}],"jlptLevel":"N2"},{"id":"k097","character":"耗","onyomi":["しょうも"],"kunyomi":[],"meaning":"消耗（exhaustion","examples":[{"word":"消耗","reading":"しょうもう","meaning":"消耗（exhaustion, consumption）"}],"jlptLevel":"N2"},{"id":"k098","character":"助","onyomi":["じょきょ"],"kunyomi":[],"meaning":"助教授（assistant professor）","examples":[{"word":"助教授","reading":"じょきょうじゅ","meaning":"助教授（assistant professor）"}],"jlptLevel":"N2"},{"id":"k099","character":"教","onyomi":["じょきょ"],"kunyomi":[],"meaning":"助教授（assistant professor）","examples":[{"word":"助教授","reading":"じょきょうじゅ","meaning":"助教授（assistant professor）"},{"word":"～教","reading":"～きょう","meaning":"～教（religion）"},{"word":"教養","reading":"きょうよう","meaning":"教養（culture, education, sophistication）"}],"jlptLevel":"N2"},{"id":"k100","character":"授","onyomi":["じょきょ"],"kunyomi":[],"meaning":"助教授（assistant professor）","examples":[{"word":"助教授","reading":"じょきょうじゅ","meaning":"助教授（assistant professor）"}],"jlptLevel":"N2"}]